discordtools/cli.py
discordtools-0.1.1.dist-info/entry_points.txt
discordtools-0.1.1.dist-info/WHEEL
discordtools-0.1.1.dist-info/METADATA
discordtools-0.1.1.dist-info/RECORD
