Metadata-Version: 2.1
Name: discordtools
Version: 0.1.1
Summary: 
Author: Marco Rougeth
Author-email: pypi@rougeth.com
Requires-Python: >=3.9,<4.0
Classifier: Programming Language :: Python :: 3
Classifier: Programming Language :: Python :: 3.10
Classifier: Programming Language :: Python :: 3.9
Requires-Dist: click (>=8.0.3,<9.0.0)
Requires-Dist: discord.py (>=1.7.3,<2.0.0)
Requires-Dist: rich (>=10.12.0,<11.0.0)
